Pandas0192ZhongwenWendang20170305/README.md
Pandas0192ZhongwenWendang20170305/__init__.py
Pandas0192ZhongwenWendang20170305/__main__.py
Pandas0192ZhongwenWendang20170305/file.epub
Pandas0192ZhongwenWendang20170305/index.html
Pandas0192ZhongwenWendang20170305/css/__init__.py
Pandas0192ZhongwenWendang20170305/css/annotations.css
Pandas0192ZhongwenWendang20170305/css/main.css
Pandas0192ZhongwenWendang20170305/css/normalize.css
Pandas0192ZhongwenWendang20170305/css/popup.css
Pandas0192ZhongwenWendang20170305/font/__init__.py
Pandas0192ZhongwenWendang20170305/font/fontello.eot
Pandas0192ZhongwenWendang20170305/font/fontello.svg
Pandas0192ZhongwenWendang20170305/font/fontello.ttf
Pandas0192ZhongwenWendang20170305/font/fontello.woff
Pandas0192ZhongwenWendang20170305/img/__init__.py
Pandas0192ZhongwenWendang20170305/img/annotator-glyph-sprite.png
Pandas0192ZhongwenWendang20170305/img/annotator-icon-sprite.png
Pandas0192ZhongwenWendang20170305/img/apple-touch-icon.png
Pandas0192ZhongwenWendang20170305/img/cancelfullscreen.png
Pandas0192ZhongwenWendang20170305/img/close.png
Pandas0192ZhongwenWendang20170305/img/fullscreen.png
Pandas0192ZhongwenWendang20170305/img/loader.gif
Pandas0192ZhongwenWendang20170305/img/menu-icon.png
Pandas0192ZhongwenWendang20170305/img/save.png
Pandas0192ZhongwenWendang20170305/img/saved.png
Pandas0192ZhongwenWendang20170305/img/settings-s.png
Pandas0192ZhongwenWendang20170305/img/settings.png
Pandas0192ZhongwenWendang20170305/img/star.png
Pandas0192ZhongwenWendang20170305/js/__init__.py
Pandas0192ZhongwenWendang20170305/js/epub.js
Pandas0192ZhongwenWendang20170305/js/epub.min.js
Pandas0192ZhongwenWendang20170305/js/epub.min.map
Pandas0192ZhongwenWendang20170305/js/hooks.min.js
Pandas0192ZhongwenWendang20170305/js/hooks.min.map
Pandas0192ZhongwenWendang20170305/js/reader.js
Pandas0192ZhongwenWendang20170305/js/reader.js.map
Pandas0192ZhongwenWendang20170305/js/reader.min.js
Pandas0192ZhongwenWendang20170305/js/reader.min.map
pandas_0_19_2_zhongwen_wendang_20170305-2024.3.2.0.dist-info/METADATA
pandas_0_19_2_zhongwen_wendang_20170305-2024.3.2.0.dist-info/WHEEL
pandas_0_19_2_zhongwen_wendang_20170305-2024.3.2.0.dist-info/entry_points.txt
pandas_0_19_2_zhongwen_wendang_20170305-2024.3.2.0.dist-info/top_level.txt
pandas_0_19_2_zhongwen_wendang_20170305-2024.3.2.0.dist-info/RECORD
